natal_report/__init__.py
natal_report/report.css
natal_report/report.py
natal_report-0.1.6.dist-info/METADATA
natal_report-0.1.6.dist-info/WHEEL
natal_report-0.1.6.dist-info/licenses/LICENSE
natal_report-0.1.6.dist-info/RECORD
