Metadata-Version: 2.4
Name: natal-report
Version: 0.1.6
Summary: generate PDF report for the Natal package
Project-URL: License, https://opensource.org/licenses/MIT
Project-URL: repository, https://github.com/hoishing/natal-report
License: MIT
License-File: LICENSE
Requires-Python: >=3.12
Requires-Dist: natal>=0.9.3
Requires-Dist: weasyprint>=64.1
